oidc/__init__.py
oidc/apps.py
oidc/constants.py
oidc/provider.py
oidc/templates/oidc/configure.html
oidc/views.py
sentry_auth_oidc-9.1.0.dist-info/LICENSE
sentry_auth_oidc-9.1.0.dist-info/METADATA
sentry_auth_oidc-9.1.0.dist-info/WHEEL
sentry_auth_oidc-9.1.0.dist-info/entry_points.txt
sentry_auth_oidc-9.1.0.dist-info/RECORD
