Metadata-Version: 2.3
Name: sentry-auth-oidc
Version: 9.1.0
Summary: OpenID Connect authentication provider for Sentry
License: Apache 2.0
Author: Max Wittig
Author-email: max.wittig@siemens.com
Requires-Python: >=3.11,<4.0
Classifier: Intended Audience :: Developers
Classifier: Intended Audience :: System Administrators
Classifier: License :: Other/Proprietary License
Classifier: Operating System :: OS Independent
Classifier: Programming Language :: Python :: 3
Classifier: Programming Language :: Python :: 3.11
Classifier: Programming Language :: Python :: 3.12
Classifier: Programming Language :: Python :: 3.13
Classifier: Topic :: Software Development
